README.md
package_info.json
setup.py
th2_grpc_generator_template/Bar.proto
th2_grpc_generator_template/Bar_pb2.py
th2_grpc_generator_template/Bar_pb2_grpc.py
th2_grpc_generator_template/Bar_service.py
th2_grpc_generator_template/Foo.proto
th2_grpc_generator_template/Foo_pb2.py
th2_grpc_generator_template/Foo_pb2_grpc.py
th2_grpc_generator_template/Foo_service.py
th2_grpc_generator_template/__init__.py
th2_grpc_generator_template.egg-info/PKG-INFO
th2_grpc_generator_template.egg-info/SOURCES.txt
th2_grpc_generator_template.egg-info/dependency_links.txt
th2_grpc_generator_template.egg-info/requires.txt
th2_grpc_generator_template.egg-info/top_level.txt