Metadata-Version: 2.1
Name: th2-grpc-generator-template
Version: 1.2.4
Summary: th2_grpc_generator_template
Home-page: https://github.com/th2-net/th2-grpc-generator-template
Author: TH2-devs
Author-email: th2-devs@exactprosystems.com
License: Apache License 2.0
Platform: UNKNOWN
Requires-Python: >=3.7
